mcp_sse_proxy.py
mcp_sse_proxy-0.1.4.dist-info/licenses/LICENSE
mcp_sse_proxy-0.1.4.dist-info/METADATA
mcp_sse_proxy-0.1.4.dist-info/WHEEL
mcp_sse_proxy-0.1.4.dist-info/entry_points.txt
mcp_sse_proxy-0.1.4.dist-info/top_level.txt
mcp_sse_proxy-0.1.4.dist-info/RECORD
