Metadata-Version: 2.4
Name: mcp-sse-proxy
Version: 0.1.4
Summary: Proxy between MCP server using STDIO transport and client using SSE transport
Home-page: https://github.com/getsimpletool/mcp-sse-proxy
Author: Artur Zdolinski
Author-email: artur@zdolinski.com
Classifier: Programming Language :: Python :: 3
Classifier: License :: OSI Approved :: MIT License
Classifier: Operating System :: OS Independent
Requires-Python: >=3.10
License-File: LICENSE
Requires-Dist: httpx>=0.24.0
Requires-Dist: anyio>=4.7.0
Requires-Dist: python-dotenv
Dynamic: author
Dynamic: author-email
Dynamic: classifier
Dynamic: home-page
Dynamic: license-file
Dynamic: requires-dist
Dynamic: requires-python
Dynamic: summary
